Workbook
Name \0: #N/A
Name \123: '[1]foreign travel'!#REF!
Name \a: #REF!
Name \A: #REF!
Name \a1: #REF!
Name \a1: #REF!
Name \aa: #REF!
Name \an: #REF!
Name \anj: #REF!
Name \ath: #REF!
Name \b: [2]事務所引越見積書!#REF!
Name \b: #REF!
Name \bbb: #REF!
Name \c: #REF!
Name \C: #REF!
Name \d: #REF!
Name \d: #REF!
Name \dd: #REF!
Name \e: #REF!
Name \e: #REF!
Name \f: #REF!
Name \f: #REF!
Name \ff: #REF!
Name \g: #REF!
Name \g: #REF!
Name \H: #REF!
Name \I: #REF!
Name \j: #REF!
Name \K: #REF!
Name \L: #REF!
Name \m: #REF!
Name \m: #REF!
Name \n: #REF!
Name \n: #REF!
Name \o: #N/A
Name \p: #REF!
Name \P: [3]BAL.SHEET!#REF!
Name \pro: #REF!
Name \q: #N/A
Name \r: #REF!
Name \r: #REF!
Name \s: #REF!
Name \S: [3]BAL.SHEET!#REF!
Name \t: #REF!
Name \t: #REF!
Name \U: #REF!
Name \W: #REF!
Name \x: #N/A
Name \Y: #REF!
Name \z: #REF!
Name \Z: #REF!
Name \zzzzzzzzzzzzzzzzzzzzzzzzzzzzzzzzzzzzzzzzzzzzzzzzzzzzzzzzzzzzzzzzzzzzzzz: #REF!
Name _: NA()
Name _?: NA()
Name _?_w: [4]보고서!#REF!
Name _?_컛?___i: NA()
Name _?t2: [5]현금경비중역!#REF!
Name _?t2: [5]현금경비중역!#REF!
Name _?춮t2: [5]현금경비중역!#REF!
Name _?춮ta: [5]현금경비중역!#REF!

Sheet Non PD Input sheet
A2: ID | B2: Division | C2: Category | D2: Group | E2: Location | F2: Project Unit | G2: Item Description | H2: Current Scenario And Justification | I2: Deliverables KPI | J2: Budget Based On | K2: Request For | L2: Financial | M2: Project Owner | N2: Expenditure Type | O2: Template Category | P2: ProjectName | Q2: Vital | R2: Essential | S2: Desirable | T2: Quantity | U2: Unit Of Measure | V2: Unit Rate | W2: Currency | X2: Exchange rate | Y2: Basic In Lacs | Z2: Type of Purchase | AA2: NR Tax Percentage | AB2: NetCost | AC2: Project Total Commitment | AD2: Project Total CashFlow | AE2: FY 1 Commitment | AF2: FY 1 CashFlow | AG2: FY 2 Commitment | AH2: FY 2 CashFlow | AI2: FY 3 Commitment | AJ2: FY 3 CashFlow | AK2: FY 4 Commitment | AL2: FY 4 CashFlow | AM2: FY 5 Commitment | AN2: FY 5 CashFlow
A3: ProjectId - Auto | B3: Dropdown | C3: capacity expansion | D3: Dropdown | E3: Dropdown | F3: Dropdown | G3: input | H3: input | I3: input | J3: Dropdown | K3: Dropdown | L3: Dropdown | M3: employee master | N3: Dropdown | O3: Dropdown | P3: Dropdown | Q3: input | R3: input | S3: input | T3: input | U3: Dropdown | V3: input | W3: Dropdown | X3: input | Y3: unit rate * quantity | Z3: dropdown | AA3: gst rate (18%) | AB3: (basic in lacs * tax) + basic | AC3: =AE3+AG3+AI3+AK3+AM3 -> 1.52 | AD3: =AF3+AH3+AJ3+AL3+AN3 -> 1.52 | AE3: ='Budget Inputs for NON PD'!I3 -> 0.97 | AF3: ='Budget Inputs for NON PD'!I4 -> 0.75 | AG3: ='Budget Inputs for NON PD'!X3+'Budget Inputs for NON PD'!Y3 -> 0.45 | AH3: ='Budget Inputs for NON PD'!X4+'Budget Inputs for NON PD'!Y4 -> 0.22 | AI3: ='Budget Inputs for NON PD'!Z3+'Budget Inputs for NON PD'!AA3 -> 0.1 | AJ3: ='Budget Inputs for NON PD'!Z4+'Budget Inputs for NON PD'!AA4 -> 0.55 | AK3: ='Budget Inputs for NON PD'!AB3+'Budget Inputs for NON PD'!AC3 -> 0 | AL3: ='Budget Inputs for NON PD'!AB4+'Budget Inputs for NON PD'!AC4 -> 0 | AM3: ='Budget Inputs for NON PD'!AD3+'Budget Inputs for NON PD'!AE3 -> 0 | AN3: ='Budget Inputs for NON PD'!AD4+'Budget Inputs for NON PD'!AE4 -> 0
B4: SML | C4: safety & comp. | D4: Chassis | E4: Ropar | F4: paint shop | J4: estimation | K4: addition | L4: IRR | M4: department wise | N4: Capex | O4: manu sir sharing | P4: stand alone | T4: decimal as well | U4: old budget portal have | V4: decimal | W4: all currencies | Y4: unit rate * exch rate * quantity | Z4: local | AA4: dynamic | AC4: DERIVED FROM SECOND SCREEN
B5: MTB | C5: quality | D5: BUS | E5: Chd | F5: engine shop | J5: quotation | K5: replacment | L5: Non IRR | N5: DRE | Z5: import
C6: sustainance | D6: R & D | E6: Zonal offices locations | F6: store | J6: repeat order | K6: reconditioning | Z6: civil
C7: Replacement | D7: SPD | K7: new
D8: Servicing | K8: upgradation
D9: Mkt & Sales
D10: All departments
D13: HO Admin
D14: Zonal Office/Area O.

Sheet Budget Inputs for NON PD
A2: ID | B2: Division | C2: Category | D2: Group | E2: Location | F2: Project Unit | G2: Item Description | I2: FY 1 | J2: Apr | K2: May | L2: Jun | M2: Jul | N2: Aug | O2: Sep | P2: Oct | Q2: Nov | R2: Dec | S2: Jan | T2: Feb | U2: Mar | V2: H1 FY 1 | W2: H2 FY 1 | X2: H1 FY2 | Y2: H2 FY2 | Z2: H1 FY3 | AA2: H2 FY3 | AB2: H1 FY 4 | AC2: H2 FY 4 | AD2: H1 FY 5 | AE2: H2 FY 5
H3: Commitment | I3: =SUM(J3:U3) -> 0.97 | J3: 0.25 | L3: 0.5 | Q3: 0.22 | V3: =SUM(J3:O3) -> 0.75 | W3: =SUM(P3:U3) -> 0.22 | Y3: 0.45 | Z3: 0.1
A4: WILL BE PICKED FROM PREVIOUS SCREEN | H4: CashFlow | I4: =SUM(J4:U4) -> 0.75 | L4: 0.25 | N4: 0.5 | V4: =SUM(J4:O4) -> 0.75 | W4: =SUM(P4:U4) -> 0 | X4: 0.22 | Z4: 0.45 | AA4: 0.1

Sheet Sheet2
A1: Column Names
A2: NonPDDetailId
A3: ProejctId
A4: RecordId
A5: DeptId
A6: IsDeleted
A7: DraftStatus
A8: Id
A9: Division
A10: Category
A11: Group
A12: Location
... A75: CF_Fy4H2

Sheet PD Input sheet 2
A3: Sr no | B3: Project name | C3: Category | D3: Capex Bifurcation Rs. In cr | AB3: Revex Bifurcation Rs. In cr | AZ3: Carry Forward | BD3: Actual Spent till Mar'26 | BL3: Fund Flow FY 27 | CN3: Fund Flow FY 28 | CR3: Fund Flow FY 29 | CV3: Fund Flow FY 30 | CZ3: Fund Flow FY 31 | DD3: C/f Fund Flow FY 27
D4: PD | J4: CDMM | P4: CME-Ch | V4: CME-Bus | AB4: PD | AH4: CDMM | AN4: CME-Ch | AT4: CME-Bus | AZ4: PD | BA4: CDMM | BB4: CME-Chassis | BC4: CME-BB | BD4: PD | BF4: CDMM | BH4: CME-Chassis | BJ4: CME-BB | BL4: PD | BS4: CDMM | BZ4: CME-Chassis | CG4: CME-BB | CN4: PD | CO4: CDMM | CP4: CME-CH | CQ4: CME-B | CR4: PD | CS4: CDMM | CT4: CME-CH | CU4: CME-B | CV4: PD | CW4: CDMM | CX4: CME-CH | CY4: CME-B | CZ4: PD | DA4: CDMM | DB4: CME-CH | DC4: CME-B | DD4: PD | DK4: CDMM | DR4: CME-Chassis | DY4: CME-BB
D5: Remarks | E5: Total PR | F5: FY27H1 | G5: FY27H2 | H5: FY 28 | I5: FY 29 | J5: Remarks | K5: Total PR | L5: FY27H1 | M5: FY27H2 | N5: FY 28 | O5: FY 29 | P5: Remarks | Q5: Total PR | R5: FY27H1 | S5: FY27H2 | T5: FY 28 | U5: FY 29 | V5: Remarks | W5: Total PR | X5: FY27H1 | Y5: FY27H2 | Z5: FY 28 | AA5: FY 29 | AB5: Remarks | AC5: Total PR | AD5: FY27H1 | AE5: FY27H2 | AF5: FY 28 | AG5: FY 29 | AH5: Remarks | AI5: Total PR | AJ5: FY27H1 | AK5: FY27H2 | AL5: FY 28 | AM5: FY 29 | AN5: Remarks | AO5: Total PR | AP5: FY27H1 | AQ5: FY27H2 | AR5: FY 28 | AS5: FY 29 | AT5: Remarks | AU5: Total PR | AV5: FY27H1 | AW5: FY27H2 | AX5: FY 28 | AY5: FY 29 | BD5: Capex | BE5: Revex | BF5: Capex | BG5: Revex | BH5: Capex | BI5: Revex | BJ5: Capex | BK5: Revex | BL5: Total | BM5: H1 | BN5: H2 | BO5: Cap H1 | BP5: Cap H2 | BQ5: Rev H1 | BR5: Rev H2 | BS5: Total | BT5: H1 | BU5: H2 | BV5: Cap H1 | BW5: Cap H2 | BX5: Rev H1 | BY5: Rev H2 | BZ5: Total | CA5: H1 | CB5: H2 | CC5: Cap H1 | CD5: Cap H2 | CE5: Rev H1 | CF5: Rev H2 | CG5: Total | CH5: H1 | CI5: H2 | CJ5: Cap H1 | CK5: Cap H2 | CL5: Rev H1 | CM5: Rev H2 | DD5: Total | DE5: H1 | DF5: H2 | DG5: Cap H1 | DH5: Cap H2 | DI5: Rev H1 | DJ5: Rev H2 | DK5: Total | DL5: H1 | DM5: H2 | DN5: Cap H1 | DO5: Cap H2 | DP5: Rev H1 | DQ5: Rev H2 | DR5: Total | DS5: H1 | DT5: H2 | DU5: Cap H1 | DV5: Cap H2 | DW5: Rev H1 | DX5: Rev H2 | DY5: Total | DZ5: H1 | EA5: H2 | EB5: Cap H1 | EC5: Cap H2 | ED5: Rev H1 | EE5: Rev H2

Sheet Sheet1
A3: Sr no | B3: Project ID | C3: Project Name | D3: Category | E3: Project name | F3: Scope
A7: PD Cap | B7: Revenue - PVH & Engg. | C7: Amount | D7: Capex Bifurcation Rs. In cr | J7: Revex Bifurcation Rs. In cr | P7: Carry Forward | Q7: Actual Spent till Mar'26 | S7: Fund Flow FY 27 | Z7: Fund Flow FY 28 | AA7: Fund Flow FY 29 | AB7: Fund Flow FY 30 | AC7: Fund Flow FY 31 | AD7: C/f Fund Flow FY 27
D8: PD | J8: PD | P8: PD | Q8: PD | S8: PD | Z8: PD | AA8: PD | AB8: PD | AC8: PD | AD8: PD
D9: Remarks | E9: Total PR | F9: FY27H1 | G9: FY27H2 | H9: FY 28 | I9: FY 29 | J9: Remarks | K9: Total PR | L9: FY27H1 | M9: FY27H2 | N9: FY 28 | O9: FY 29 | Q9: Capex | R9: Revex | S9: Total | T9: H1 | U9: H2 | V9: Cap H1 | W9: Cap H2 | X9: Rev H1 | Y9: Rev H2 | AD9: Total | AE9: H1 | AF9: H2 | AG9: Cap H1 | AH9: Cap H2 | AI9: Rev H1 | AJ9: Rev H2
A10: Veh Cap - 18 nos (Total) | B10: CDC, Static barke (Part-4)- Engine connected, PHML + HML | C10: 12

Sheet PD Input Sheet 1
D1: 2
B2: Sr. No. | C2: Project | D2: Scope | E2: PD Cap | F2: Revenue - PVH & Engg. | H2: Cap-CDMM | J2: Rev-CDMM | L2: Cap-CME- Plant Engg | N2: Rev-CME | P2: Cap-Powertrain Division | R2: Rev-Powertrain Division | T2: Cap - Total | U2: Rev - Total | V2: Total
B3: 1 | C3: xxxxx | D3: Model: XXX, YYY, ZZZ, ++ Clutch change from 395mm to 430mm ROD type GSM | E3: =(34*16)+28 -> 572 | F3: =SUM(G4:G30) -> 1040.4 | H3: =SUM(I4:I30) -> 524 | J3: =SUM(K4:K30) -> 171.5 | L3: =SUM(M4:M26) -> 201 | N3: =O4+O5+O6 -> 1.9 | P3: =Q4+Q5+Q6+Q7+Q8+Q9+Q10+Q11+Q12+Q13+Q21+Q22+Q23+Q24+Q25 -> 195.1 | R3: =S4+S5+S6+S7+S8+S9 -> 95 | T3: =E3+H3+L3+P3 -> 1492.1 | U3: =R3+N3+J3+F3 -> 1308.8 | V3: =SUM(E3:S3) -> 2800.9
B4: Major Assumptions: PVH: All VP0 vehicles are considered as new vehicles. No 55T 4X2 vehicle available with PVH fleet PEMS & PTD calibration budget considered in PTD. Not in PD CME: No seperate budget considerd for Pokayoke requirements via QR code scanning. Bar code requrirement to be freezed at design stage & should come along with the part. CDMM: Engine Mount Budget is protected considering only Rubber change Exhaust pipe hot vibration test budget not considered under supplier DVP. Same will be confirmed post CAE completion. QP/PVH: No seperate budget considered fro RGA monitoring. Steps to be followed as below. i) RGA vaildation on DVP vehicle (in parallel to DVP on 3 vehicles ADT, GHD & RWUP) ii) RGA verification seeding batch of VP build Hence, no seperate budget considered | E4: Veh Cap - 18 nos (Total) | F4: CDC, Static barke (Part-4)- Engine connected, PHML + HML | G4: =4*3 -> 12 | H4: Sheet Metal Pipe Mud Guard - (16.8L* 2) + 9.5L GSL Reinf - 13.5L Cross Member - 8.5L BRKTs - 18.7L BRKT Air Filter - 28.72 BRKT Assy Hanger - 11.42 | I4: 124 | J4: Rear Axle DVP 4.88 & 5.13 | K4: 49 | L4: GSM Pokayoke for 6S & 9S | M4: 9 | N4: Line side logistics & template | O4: 1.9 | P4: Flywheel | Q4: 7.1 | R4: Crankshaft modal bending , torsional topology and fatigue analysis - Simulation | S4: 25
E5: 55T 4X2 - 5 Nos | F5: IQA, Installation, In-cab noise (28T tip & 48T Cargo), Dust ingress, Hot air entry & water wading, Mudguard installation & spray suppression. Thermal measurement at GSM cutout. Cabin cut-out & GSM bellow interface check- Component & GHD Rod type shifter functionality | G5: =8+1+1 -> 10 | H5: Casting Forging Rear Mount BRKT (LH & RH) 8L per tool Rear Axle Shaft - 5L | I5: 21 | J5: GSM DVP | K5: 51 | L5: Cabin - Floor modification | M5: 21 | P5: Flywheel housing | Q5: 14.2 | R5: Engine DVP (1000hrs) | S5: 35
E6: 55T 6X4 - 1 Nos | F6: Chassis DVP, CRF, Installation, | G6: =7*1 -> 7 | H6: Electricals Wire Harness - All models | I6: 33 | J6: Engine Mount DVP | K6: 18 | L6: Pokayoke - 7.5L Tools - 27.5L FTG - 17L | M6: 52 | P6: Ring Gear | Q6: 8.3 | R6: PEMS & Engine Homologation | S6: 22
E7: 28T TP - 4 nos | F7: Clutch DVP (Gradability, Clutch drop & Stall), Hill start. | G7: =5*3 -> 15 | H7: Plastic & Rubber Air Filter Duct - x Lacs Clean side Duct - yy Lacs Hoses - zz Lacs Duct Pre Cleaner - rr Lacs Rubber Beading - 6 L | I7: 66 | J7: Proto Parts Sheet Metal: 6L Engine Mounts: 15L GSM Proto: 20L | K7: 44 | L7: DC tool - 2nos | M7: 64 | P7: Assy Pipe, Fuel Line Brkt , Cover fly wheel hsg | Q7: 8.2 | R7: CME - Rev | S7: 1
E8: 35 TP - 3 nos | F8: Electrical DVP, Installation, CRF, Errors check | G8: 25 | H8: Prop: GSM - 108L (ZF + Eaton) Rear Axle - 32L Assy Pipe Flex - 12L | I8: 154 | J8: Brakes DVP | K8: 4 | L8: Required storage space for engine, transmission, clutch housing, axle, propeller shaft (120sq.m) - creating space by Mezzanine floor | M8: 40 | P8: Flywheel testing adaptor | Q8: 28 | R8: Proto Cost - Transmission | S8: 9
E9: 48T Cargo - 3 nos | F9: Engine DVP, IQA, Inclination angle, Fan dutycycle, IOBD, Engine overrun, Eng. Mount displacement, Engine mount Isolation -By NVH , Articulation | G9: =6+3 -> 9 | H9: Mounts | I9: 63 | J9: CCA+Fuel Syst DVP | K9: 5.5 | L9: Cabin - Die Modification in BIW | M9: 15 | P9: Flywheel & hosing Manipulator & tackle | Q9: 64 | R9: DVP - Transmission | S9: 3
E10: 48T HT - 1 nos | F10: Fuel DVP, Exhaust DVP, Air intake DVP Articulation, CRF, Installation. | G10: =6+(4*2) -> 14 | H10: Trolley, Bins & PP Box | I10: 63 | P10: Part storage facility & Part feeding trolly | Q10: 5.3
E11: 49T Cargo - 1 nos | F11: Prop shaft DVP, IQA, Beta angle, | G11: =2+1+1 -> 4 | P11: Pallet Modification | Q11: 7
E12: 2 New trailers - 28L (14L/Trailer) | F12: Axle DVP - Installation, Max speed, SLF, Noise, HML | G12: 12 | P12: Clutch housing+ Release fork+ GB lever | Q12: 53
F13: Trans DVP (Rod type GSM), GSQA, GSD, Gear jump-out, GSM lever vibration and clearances with cabin cut-out. Articulation trials. | G13: =10*2 -> 20
F14: Driveability, FE & Performance Base vehicle - 5L (MTBD) Benchmark vehicle (Rent + Testing) - 15L | G14: =(20*2+10*4) -> 80
F15: Cost for 18 vehicles conversion (1.5L per vehicle) | G15: =18*1.5 -> 27
F16: Benchmarking for 1 models (20k/day for 1 veh-1 months) | G16: 25
F17: Benchmark validation | G17: 0
F18: All component testing (Major Aggregates: Cross Member, GSM, Fuel Lines, Clutch) | G18: 15
F19: RLDA & ADT for 5500 Km (₹1000/- per km) | G19: =5500*(1000/100000) -> 55
F20: GHD for 80K Km (₹100/- per km) for 2 vehicles | G20: =2*80000*(100/100000) -> 160
F21: Tip Trailer, POL etc. applications - RWUP for 80K Km (₹100/- per km) | G21: =2*180 -> 360
F22: Jury trials | G22: =5*3 -> 15
F23: Pre Homologation | G23: =10*3 -> 30
F24: Homologation certification | G24: =4*7 -> 28
F25: Seeding for 50 Vehicles | G25: =4*7 -> 28
F26: PP vehicle verification (repeat trials) | G26: =2*3 -> 6
F27: AVL Consultancy Charges | G27: 0
F28: Protoshop for manpower - PVH | G28: 15
F29: Resources manpower for Engg - Contingency | G29: =4*6*1.25*1.18 -> 35.4
F30: Platform Contingency | G30: =33 -> 33
AP32: Project Name | AQ32: PD Capex | AU32: PD Rev | AY32: CDMM Capex | BC32: CDMM Rev | BG32: CME Capex | BK32: CME Rev | BO32: PTD Capex | BS32: PTD Rev | BW32: Capex | CA32: Rev | CE32: Total Budget | CF32: Cap Total | CG32: Rev Total
AP33: 430 Dia Clutch - Total Budget | AQ33: =E3 -> 572 | AU33: =F3 -> 1040.4 | AY33: =H3 -> 524 | BC33: =J3 -> 171.5 | BG33: 201 | BK33: 1.9 | BO33: 195.1 | BS33: 95 | BW33: Q1 | BX33: Q2 | BY33: Q3 | BZ33: Q4 | CA33: Q1 | CB33: Q2 | CC33: Q3 | CD33: Q4 | CE33: =SUM(CF33:CG34) -> 2858.7 | CF33: =SUM(BW35:BZ40) -> 1549.9 | CG33: =SUM(CA35:CD40) -> 1308.8
AQ34: Q1 | AR34: Q2 | AS34: Q3 | AT34: Q4 | AU34: Q1 | AV34: Q2 | AW34: Q3 | AX34: Q4 | AY34: Q1 | AZ34: Q2 | BA34: Q3 | BB34: Q4 | BC34: Q1 | BD34: Q2 | BE34: Q3 | BF34: Q4 | BG34: Q1 | BH34: Q2 | BI34: Q3 | BJ34: Q4 | BK34: Q1 | BL34: Q2 | BM34: Q3 | BN34: Q4 | BO34: Q1 | BP34: Q2 | BQ34: Q3 | BR34: Q4 | BS34: Q1 | BT34: Q2 | BU34: Q3 | BV34: Q4
AP35: F25 Total | AQ35: =AQ33*0.85 -> 486.2 | AU35: =AU33*0.2 -> 208.08 | AY35: =AY33*0.7 -> 366.8 | BC35: =BC33*0.4 -> 68.6 | BG35: =BG33 -> 201 | BK35: 1.9 | BO35: =BO33 -> 195.1 | BS35: 95 | BW35: =AQ36+AY36+BG36+BO36 -> 0 | BX35: =AR36+AZ36+BH36+BP36 -> 444.68 | BY35: =AS36+BA36+BI36+BQ36 -> 346.86 | BZ35: =AT36+BB36+BJ36+BR36 -> 515.36 | CA35: =AU36+BC36+BK36+BS36 -> 41.616 | CB35: =AV36+BD36+BL36+BT36 -> 41.616 | CC35: =AW36+BE36+BM36+BU36 -> 132.916 | CD35: =AX36+BF36+BN36+BV36 -> 157.432 | CE35: 1771 | CF35: =SUM(BW35:BZ36) -> 1306.9 | CG35: =SUM(CA35:CD36) -> 373.58
AP36: F25 Quarterwirse | AQ36: 0 | AR36: 0 | AS36: =3*34 -> 102 | AT36: =34*13 -> 442 | AU36: =AU35*0.2 -> 41.616 | AV36: =AU35*0.2 -> 41.616 | AW36: =AU35*0.2 -> 41.616 | AX36: =AU35*0.4 -> 83.232 | AY36: 0 | AZ36: =AY35*0.4 -> 146.72 | BA36: =AY35*0.4 -> 146.72 | BB36: =AY35*0.2 -> 73.36 | BC36: 0 | BD36: 0 | BE36: =BC35*0.5 -> 34.3 | BF36: =BC35*0.5 -> 34.3 | BG36: 0 | BH36: =BG35*0.9 -> 180.9 | BI36: =BG35*0.1 -> 20.1 | BJ36: 0 | BK36: 0 | BL36: 0 | BM36: 0 | BN36: =BK35 -> 1.9 | BO36: 0 | BP36: =BO35*0.6 -> 117.06 | BQ36: =BO35*0.4 -> 78.04 | BR36: 0 | BS36: 0 | BT36: 0 | BU36: =BS35*0.6 -> 57 | BV36: =BS35*0.4 -> 38
AP37: F26 Total | AQ37: =AQ33*0.15 -> 85.8 | AU37: =AU33*0.7 -> 728.28 | AY37: =AY33*0.3 -> 157.2 | BC37: =BC33*0.4 -> 68.6 | BG37: 0 | BK37: 0 | BO37: 0 | BS37: 0 | BW37: =AQ38+AY38+BG38+BO38 -> 164.4 | BX37: =AR38+AZ38+BH38+BP38 -> 78.6 | BY37: =AS38+BA38+BI38+BQ38 -> 0 | BZ37: =AT38+BB38+BJ38+BR38 -> 0 | CA37: =AU38+BC38+BK38+BS38 -> 252.784 | CB37: =AV38+BD38+BL38+BT38 -> 252.784 | CC37: =AW38+BE38+BM38+BU38 -> 218.484 | CD37: =AX38+BF38+BN38+BV38 -> 72.828 | CE37: 623.6 | CF37: =SUM(BW37:BZ38) -> 243 | CG37: =SUM(CA37:CD38) -> 796.88
AP38: F26 Quarterwirse | AQ38: =AQ37 -> 85.8 | AR38: 0 | AS38: 0 | AT38: 0 | AU38: =AU37*0.3 -> 218.484 | AV38: =AU37*0.3 -> 218.484 | AW38: =AU37*0.3 -> 218.484 | AX38: =AU37*0.1 -> 72.828 | AY38: =AY37*0.5 -> 78.6 | AZ38: =AY37*0.5 -> 78.6 | BA38: 0 | BB38: 0 | BC38: =+BC37*0.5 -> 34.3 | BD38: =BC37*0.5 -> 34.3 | BE38: 0 | BF38: 0 | BG38: =BG37*0.5 -> 0 | BH38: =BG37*0.5 -> 0 | BI38: 0 | BJ38: 0 | BK38: 0 | BL38: 0 | BM38: 0 | BN38: 0 | BO38: =BO37*0.5 -> 0 | BP38: =BO37*0.5 -> 0 | BQ38: 0 | BR38: 0 | BS38: 0 | BT38: 0 | BU38: 0 | BV38: 0
AP39: F27 Total | AQ39: 0 | AU39: =AU33*0.1 -> 104.04 | AY39: 0 | BC39: =BC33*0.2 -> 34.3 | BG39: 0 | BK39: 0 | BO39: 0 | BS39: 0 | BW39: =AQ40+AY40+BG40+BO40 -> 0 | BX39: =AR40+AZ40+BH40+BP40 -> 0 | BY39: =AS40+BA40+BI40+BQ40 -> 0 | BZ39: =AT40+BB40+BJ40+BR40 -> 0 | CA39: =AU40+BC40+BK40+BS40 -> 86.32 | CB39: =AV40+BD40+BL40+BT40 -> 52.02 | CC39: =AW40+BE40+BM40+BU40 -> 0 | CD39: =AX40+BF40+BN40+BV40 -> 0 | CE39: 140 | CF39: =SUM(BW39:BZ40) -> 0 | CG39: =SUM(CA39:CD40) -> 138.34
AP40: F27 Quarterwirse | AQ40: 0 | AR40: 0 | AS40: 0 | AT40: 0 | AU40: =AU39*0.5 -> 52.02 | AV40: =AU39*0.5 -> 52.02 | AW40: 0 | AX40: 0 | AY40: 0 | AZ40: 0 | BA40: 0 | BB40: 0 | BC40: =BC39 -> 34.3 | BD40: 0 | BE40: 0 | BF40: 0 | BG40: 0 | BH40: 0 | BI40: 0 | BJ40: 0 | BK40: 0 | BL40: 0 | BM40: 0 | BN40: 0 | BO40: 0 | BP40: 0 | BQ40: 0 | BR40: 0 | BS40: 0 | BT40: 0 | BU40: 0 | BV40: 0
